{
  "organization": {
    "acronym": "HDZ",
    "is_coalition": true,
    "id": 343,
    "classification": "pg",
    "name": "Klub Hrvatske demokratske zajednice"
  },
  "created_at": "06.09.2018",
  "created_for": "05.09.2018",
  "results": [
    {
      "person": {
        "is_active": true,
        "district": [7],
        "name": "Ivan Vilibor Sin\u010di\u0107",
        "gov_id": "1288",
        "gender": "m",
        "party": {
          "acronym": "\u017divi zid, SNAGA",
          "is_coalition": false,
          "id": 319,
          "classification": "pg",
          "name": "Klub \u017divog zida i SNAGA-e"
        },
        "type": "mp",
        "id": 1288,
        "has_function": false
      },
      "ratio": 38.1620949065924
    },
    {
      "person": {
        "is_active": true,
        "district": [6],
        "name": "Branimir Bunjac",
        "gov_id": "1257",
        "gender": "m",
        "party": {
          "acronym": "\u017divi zid, SNAGA",
          "is_coalition": false,
          "id": 319,
          "classification": "pg",
          "name": "Klub \u017divog zida i SNAGA-e"
        },
        "type": "mp",
        "id": 1257,
        "has_function": false
      },
      "ratio": 37.7801638195686
    },
    {
      "person": {
        "is_active": true,
        "district": [5],
        "name": "Ivan Pernar",
        "gov_id": "1302",
        "gender": "m",
        "party": {
          "acronym": "\u017divi zid, SNAGA",
          "is_coalition": false,
          "id": 319,
          "classification": "pg",
          "name": "Klub \u017divog zida i SNAGA-e"
        },
        "type": "mp",
        "id": 1302,
        "has_function": false
      },
      "ratio": 34.9258451985513
    },
    {
      "person": {
        "is_active": true,
        "district": [8],
        "name": "Miro Bulj",
        "gov_id": "1373",
        "gender": "m",
        "party": {
          "acronym": "Most",
          "is_coalition": false,
          "id": 335,
          "classification": "pg",
          "name": "Klub Mosta nezavisnih lista"
        },
        "type": "mp",
        "id": 1373,
        "has_function": false
      },
      "ratio": 32.5369939129175
    },
    {
      "person": {
        "is_active": true,
        "district": [9],
        "name": "Marin \u0160kibola",
        "gov_id": "1275",
        "gender": "m",
        "party": {
          "acronym": "Nezavisni",
          "is_coalition": false,
          "id": 413,
          "classification": "unaligned MP",
          "name": "Klub nezavisnih"
        },
        "type": "mp",
        "id": 1275,
        "has_function": false
      },
      "ratio": 31.6802536308645
    }
  ]
}
